torchrdit/__init__.py
torchrdit/algorithm.py
torchrdit/builder.py
torchrdit/cell.py
torchrdit/constants.py
torchrdit/gds.py
torchrdit/gds_utils.py
torchrdit/layers.py
torchrdit/material_proxy.py
torchrdit/materials.py
torchrdit/observers.py
torchrdit/results.py
torchrdit/shapes.py
torchrdit/solver.py
torchrdit/utils.py
torchrdit/vector.py
torchrdit/viz.py
torchrdit-0.1.27.dist-info/METADATA
torchrdit-0.1.27.dist-info/WHEEL
torchrdit-0.1.27.dist-info/licenses/LICENSE
torchrdit-0.1.27.dist-info/RECORD
