Metadata-Version: 2.4
Name: torchrdit
Version: 0.1.27
Summary: A PyTorch based package for designing and analyzing optical devices, utilzing the Rigorous Diffraction Interface Theory (R-DIT).
Project-URL: Documentation, https://github.com/yi-huang-1/torchrdit/wiki
Project-URL: Source, https://github.com/yi-huang-1/torchrdit
Project-URL: Tracker, https://github.com/yi-huang-1/torchrdit/issues
Author-email: Yi Huang <yi_huang@student.uml.edu>, Ziwei Zhu <ziweizhu95@gmail.com>
License: GPL-3.0
License-File: LICENSE
Classifier: License :: OSI Approved :: GNU General Public License v3 (GPLv3)
Classifier: Operating System :: OS Independent
Classifier: Programming Language :: Python :: 3
Classifier: Programming Language :: Python :: 3.10
Classifier: Programming Language :: Python :: 3.11
Classifier: Programming Language :: Python :: 3.12
Classifier: Programming Language :: Python :: 3.13
Classifier: Topic :: Scientific/Engineering :: Artificial Intelligence
Classifier: Topic :: Scientific/Engineering :: Physics
Classifier: Topic :: Software Development :: Libraries :: Python Modules
Requires-Python: >=3.10
Requires-Dist: gdstk>=0.9.60
Requires-Dist: matplotlib>=3.10.3
Requires-Dist: numpy>=2.2.0
Requires-Dist: pyyaml>=6.0.2
Requires-Dist: ruff>=0.12.2
Requires-Dist: scikit-image>=0.25.2
Requires-Dist: scipy>=1.15.3
Requires-Dist: torch>=2.5.1
Requires-Dist: tqdm>=4.67.1
